gsheets_plot/__init__.py
gsheets_plot/main.py
gsheets_plot-0.2.1.dist-info/METADATA
gsheets_plot-0.2.1.dist-info/WHEEL
gsheets_plot-0.2.1.dist-info/top_level.txt
gsheets_plot-0.2.1.dist-info/RECORD
