Metadata-Version: 2.1
Name: gsheets-plot
Version: 0.2.1
Summary: Plot data from Google Sheets
Home-page: https://github.com/akhipachi/gsheets_plot
Author: Akhilesh Pachipulusu
Author-email: p.akhilesh99@gmail.com
License: MIT
Keywords: google sheets plot
Platform: UNKNOWN
Classifier: Development Status :: 3 - Alpha
Classifier: License :: OSI Approved
Classifier: Programming Language :: Python :: 3.7
Requires-Dist: matplotlib
Requires-Dist: gsheets
Requires-Dist: pandas
